CHANGES.rst
LICENSE
MANIFEST.in
README.rst
setup.py
pyramid_htmlmin/__init__.py
pyramid_htmlmin.egg-info/PKG-INFO
pyramid_htmlmin.egg-info/SOURCES.txt
pyramid_htmlmin.egg-info/dependency_links.txt
pyramid_htmlmin.egg-info/not-zip-safe
pyramid_htmlmin.egg-info/requires.txt
pyramid_htmlmin.egg-info/top_level.txt